{"data":{"rows":{"0":{"cells":[{"content":"C"},{"content":"C"}]},"1":{"cells":[{"content":"Cambodia"},{"content":"855"}]},"2":{"cells":[{"content":"Cameroon"},{"content":"237"}]},"3":{"cells":[{"content":"Canada"},{"content":"1"}]},"4":{"cells":[{"content":"Canary Islands"},{"content":"34"}]},"5":{"cells":[{"content":"Cape Verde"},{"content":"238"}]},"6":{"cells":[{"content":"Cayman Islands"},{"content":"1345"}]},"7":{"cells":[{"content":"Central African Republic"},{"content":"236"}]},"8":{"cells":[{"content":"Chad"},{"content":"235"}]},"9":{"cells":[{"content":"Chatham Islands"},{"content":"64"}]},"10":{"cells":[{"content":"Chile"},{"content":"56"}]},"11":{"cells":[{"content":"China"},{"content":"86"}]},"12":{"cells":[{"content":"Christmas Islands"},{"content":"61"}]},"13":{"cells":[{"content":"Cocos (Keeling) Islands"},{"content":"618"}]},"14":{"cells":[{"content":"Colombia"},{"content":"57"}]},"15":{"cells":[{"content":"Comoros and Mayotte"},{"content":"269"}]},"17":{"cells":[{"content":"Congo Dem. Republic of the"},{"content":"243"}]},"16":{"cells":[{"content":"Congo"},{"content":"242"}]},"19":{"cells":[{"content":"Costa Rica"},{"content":"506"}]},"18":{"cells":[{"content":"Cook Islands"},{"content":"682"}]},"21":{"cells":[{"content":"Croatia"},{"content":"385"}]},"20":{"cells":[{"content":"Cote d\u0027Ivoire"},{"content":"225"}]},"23":{"cells":[{"content":"Cyprus"},{"content":"357"}]},"22":{"cells":[{"content":"Cuba"},{"content":"53"}]},"25":{"cells":[{"content":"Czech Republic"},{"content":"420"}]},"24":{"cells":[{"content":"Cyprus North"},{"content":"357"}]}},"columns":{"0":{"cells":[{"content":"C"},{"content":"Cambodia"},{"content":"Cameroon"},{"content":"Canada"},{"content":"Canary Islands"},{"content":"Cape Verde"},{"content":"Cayman Islands"},{"content":"Central African Republic"},{"content":"Chad"},{"content":"Chatham Islands"},{"content":"Chile"},{"content":"China"},{"content":"Christmas Islands"},{"content":"Cocos (Keeling) Islands"},{"content":"Colombia"},{"content":"Comoros and Mayotte"},{"content":"Congo"},{"content":"Congo Dem. Republic of the"},{"content":"Cook Islands"},{"content":"Costa Rica"},{"content":"Cote d\u0027Ivoire"},{"content":"Croatia"},{"content":"Cuba"},{"content":"Cyprus"},{"content":"Cyprus North"},{"content":"Czech Republic"}]},"1":{"cells":[{"content":"C"},{"content":"855"},{"content":"237"},{"content":"1"},{"content":"34"},{"content":"238"},{"content":"1345"},{"content":"236"},{"content":"235"},{"content":"64"},{"content":"56"},{"content":"86"},{"content":"61"},{"content":"618"},{"content":"57"},{"content":"269"},{"content":"242"},{"content":"243"},{"content":"682"},{"content":"506"},{"content":"225"},{"content":"385"},{"content":"53"},{"content":"357"},{"content":"357"},{"content":"420"}]}}},"name":"20553372_4890450594743008141-0","originalDescription":{"filename":"20553372_4890450594743008141","uri":"http://www.numbersales.com/countrycode.jsp","arcfile":"common-crawl/parse-output/segment/1346876860611/1346926988606_102.arc.gz","arcfilePosition":20553372,"hasContentTables":true,"hasRelevantTables":false,"timestamp":1328645469000},"originalDescriptionTable":{"start":7932,"end":9352,"content":true,"relevant":true,"avgColCount":1.9230769,"colStdDeviation":0.3846154,"avgRowCount":25.0,"rowStdDeviation":0.0,"avgCellLength":7.0,"cellLengthStdDeviation":6.2864933,"rowCLC":2.25,"colCLC":-0.17694058,"colCount":2,"rowCount":26,"csvColCount":2,"linkPercentage":0.0,"formPercentage":0.0,"imagePercentage":0.0,"emptyPercentage":0.0,"digitPercentage":0.5,"textPercentage":0.5,"rowCTC":25.0,"colCTC":0.0,"language":"en","csvName":"20553372_0_5573649347925444148.csv"},"result":{"columns":{"0":true},"rows":{"0":true}}}