{"tableId":"19518036_993322645558677980-0","start":11572,"end":20253,"rowsStructured":[{"cellsStructured":[{"isLabelCell":true,"content":"Continent/Country"},{"isLabelCell":true,"content":"Available Cyl. Size"},{"isLabelCell":true,"content":"Cylinder Connections"},{"isLabelCell":true,"content":"Cylinder Connections"},{"isLabelCell":true,"content":"Cylinder Connections"}]},{"cellsStructured":[{"isLabelCell":true,"content":"?"},{"isLabelCell":true,"content":"?"},{"isLabelCell":true,"content":"N2"},{"isLabelCell":true,"content":"He"},{"isLabelCell":true,"content":"Ar"}]},{"cellsStructured":[{"isLabelCell":true,"content":"Asia"},{"isLabelCell":false,"content":"L and packs","columnLabels":["Asia"],"rowLabels":["Available Cyl. Size","?"]},{"isLabelCell":false,"content":"BS3","columnLabels":["Asia"],"rowLabels":["Cylinder Connections","N2"]},{"isLabelCell":false,"content":"BS3","columnLabels":["Asia"],"rowLabels":["Cylinder Connections","He"]},{"isLabelCell":false,"content":"?","columnLabels":["Asia"],"rowLabels":["Cylinder Connections","Ar"]}]},{"cellsStructured":[{"isLabelCell":true,"content":"Belgium"},{"isLabelCell":false,"content":"B50 and packs","columnLabels":["Belgium"],"rowLabels":["Available Cyl. Size","?"]},{"isLabelCell":false,"content":"Din 6","columnLabels":["Belgium"],"rowLabels":["Cylinder Connections","N2"]},{"isLabelCell":false,"content":"Din 6","columnLabels":["Belgium"],"rowLabels":["Cylinder Connections","He"]},{"isLabelCell":false,"content":"Din 6","columnLabels":["Belgium"],"rowLabels":["Cylinder Connections","Ar"]}]},{"cellsStructured":[{"isLabelCell":true,"content":"Brazil"},{"isLabelCell":false,"content":"A","columnLabels":["Brazil"],"rowLabels":["Available Cyl. Size","?"]},{"isLabelCell":false,"content":"CGA 580","columnLabels":["Brazil"],"rowLabels":["Cylinder Connections","N2"]},{"isLabelCell":false,"content":"CGA 580","columnLabels":["Brazil"],"rowLabels":["Cylinder Connections","He"]},{"isLabelCell":false,"content":"?","columnLabels":["Brazil"],"rowLabels":["Cylinder Connections","Ar"]}]},{"cellsStructured":[{"isLabelCell":true,"content":"Canada"},{"isLabelCell":false,"content":"A","columnLabels":["Canada"],"rowLabels":["Available Cyl. Size","?"]},{"isLabelCell":false,"content":"CGA 580","columnLabels":["Canada"],"rowLabels":["Cylinder Connections","N2"]},{"isLabelCell":false,"content":"CGA 580","columnLabels":["Canada"],"rowLabels":["Cylinder Connections","He"]},{"isLabelCell":false,"content":"CGA 580","columnLabels":["Canada"],"rowLabels":["Cylinder Connections","Ar"]}]},{"cellsStructured":[{"isLabelCell":true,"content":"France"},{"isLabelCell":false,"content":"B50 and packs","columnLabels":["France"],"rowLabels":["Available Cyl. Size","?"]},{"isLabelCell":false,"content":"AFNOR Type C","columnLabels":["France"],"rowLabels":["Cylinder Connections","N2"]},{"isLabelCell":false,"content":"AFNOR Type C","columnLabels":["France"],"rowLabels":["Cylinder Connections","He"]},{"isLabelCell":false,"content":"AFNOR Type C","columnLabels":["France"],"rowLabels":["Cylinder Connections","Ar"]}]},{"cellsStructured":[{"isLabelCell":true,"content":"Germany"},{"isLabelCell":false,"content":"B50 and packs","columnLabels":["Germany"],"rowLabels":["Available Cyl. Size","?"]},{"isLabelCell":false,"content":"Din 10","columnLabels":["Germany"],"rowLabels":["Cylinder Connections","N2"]},{"isLabelCell":false,"content":"Din 6","columnLabels":["Germany"],"rowLabels":["Cylinder Connections","He"]},{"isLabelCell":false,"content":"Din 6","columnLabels":["Germany"],"rowLabels":["Cylinder Connections","Ar"]}]},{"cellsStructured":[{"isLabelCell":true,"content":"India"},{"isLabelCell":false,"content":"L and packs","columnLabels":["India"],"rowLabels":["Available Cyl. Size","?"]},{"isLabelCell":false,"content":"BS3","columnLabels":["India"],"rowLabels":["Cylinder Connections","N2"]},{"isLabelCell":false,"content":"BS3","columnLabels":["India"],"rowLabels":["Cylinder Connections","He"]},{"isLabelCell":false,"content":"?","columnLabels":["India"],"rowLabels":["Cylinder Connections","Ar"]}]},{"cellsStructured":[{"isLabelCell":true,"content":"Ireland"},{"isLabelCell":false,"content":"L and packs","columnLabels":["Ireland"],"rowLabels":["Available Cyl. Size","?"]},{"isLabelCell":false,"content":"BS3","columnLabels":["Ireland"],"rowLabels":["Cylinder Connections","N2"]},{"isLabelCell":false,"content":"BS3","columnLabels":["Ireland"],"rowLabels":["Cylinder Connections","He"]},{"isLabelCell":false,"content":"BS3","columnLabels":["Ireland"],"rowLabels":["Cylinder Connections","Ar"]}]},{"cellsStructured":[{"isLabelCell":true,"content":"Italy (Sapio)"},{"isLabelCell":false,"content":"B50 and packs","columnLabels":["Italy (Sapio)"],"rowLabels":["Available Cyl. Size","?"]},{"isLabelCell":false,"content":"Uni4409","columnLabels":["Italy (Sapio)"],"rowLabels":["Cylinder Connections","N2"]},{"isLabelCell":false,"content":"Uni4412","columnLabels":["Italy (Sapio)"],"rowLabels":["Cylinder Connections","He"]},{"isLabelCell":false,"content":"Uni4412","columnLabels":["Italy (Sapio)"],"rowLabels":["Cylinder Connections","Ar"]}]},{"cellsStructured":[{"isLabelCell":true,"content":"Luxembourg"},{"isLabelCell":false,"content":"B50 and packs","columnLabels":["Luxembourg"],"rowLabels":["Available Cyl. Size","?"]},{"isLabelCell":false,"content":"Din 6","columnLabels":["Luxembourg"],"rowLabels":["Cylinder Connections","N2"]},{"isLabelCell":false,"content":"Din 6","columnLabels":["Luxembourg"],"rowLabels":["Cylinder Connections","He"]},{"isLabelCell":false,"content":"Din 6","columnLabels":["Luxembourg"],"rowLabels":["Cylinder Connections","Ar"]}]},{"cellsStructured":[{"isLabelCell":true,"content":"Mexico (Infra)"},{"isLabelCell":false,"content":"A","columnLabels":["Mexico (Infra)"],"rowLabels":["Available Cyl. Size","?"]},{"isLabelCell":false,"content":"CGA 580","columnLabels":["Mexico (Infra)"],"rowLabels":["Cylinder Connections","N2"]},{"isLabelCell":false,"content":"CGA 580","columnLabels":["Mexico (Infra)"],"rowLabels":["Cylinder Connections","He"]},{"isLabelCell":false,"content":"?","columnLabels":["Mexico (Infra)"],"rowLabels":["Cylinder Connections","Ar"]}]},{"cellsStructured":[{"isLabelCell":true,"content":"Netherlands"},{"isLabelCell":false,"content":"B50 and packs","columnLabels":["Netherlands"],"rowLabels":["Available Cyl. Size","?"]},{"isLabelCell":false,"content":"Din 10","columnLabels":["Netherlands"],"rowLabels":["Cylinder Connections","N2"]},{"isLabelCell":false,"content":"Din 10","columnLabels":["Netherlands"],"rowLabels":["Cylinder Connections","He"]},{"isLabelCell":false,"content":"Din 10","columnLabels":["Netherlands"],"rowLabels":["Cylinder Connections","Ar"]}]},{"cellsStructured":[{"isLabelCell":true,"content":"Puerto Rico"},{"isLabelCell":false,"content":"A","columnLabels":["Puerto Rico"],"rowLabels":["Available Cyl. Size","?"]},{"isLabelCell":false,"content":"CGA 580","columnLabels":["Puerto Rico"],"rowLabels":["Cylinder Connections","N2"]},{"isLabelCell":false,"content":"CGA 580","columnLabels":["Puerto Rico"],"rowLabels":["Cylinder Connections","He"]},{"isLabelCell":false,"content":"CGA 580","columnLabels":["Puerto Rico"],"rowLabels":["Cylinder Connections","Ar"]}]},{"cellsStructured":[{"isLabelCell":true,"content":"South Africa"},{"isLabelCell":false,"content":"L","columnLabels":["South Africa"],"rowLabels":["Available Cyl. Size","?"]},{"isLabelCell":false,"content":"R 3/4 Ext Male Thread","columnLabels":["South Africa"],"rowLabels":["Cylinder Connections","N2"]},{"isLabelCell":false,"content":"BS3","columnLabels":["South Africa"],"rowLabels":["Cylinder Connections","He"]},{"isLabelCell":false,"content":"BS3","columnLabels":["South Africa"],"rowLabels":["Cylinder Connections","Ar"]}]},{"cellsStructured":[{"isLabelCell":true,"content":"UK"},{"isLabelCell":false,"content":"L and packs","columnLabels":["UK"],"rowLabels":["Available Cyl. Size","?"]},{"isLabelCell":false,"content":"BS3","columnLabels":["UK"],"rowLabels":["Cylinder Connections","N2"]},{"isLabelCell":false,"content":"BS3","columnLabels":["UK"],"rowLabels":["Cylinder Connections","He"]},{"isLabelCell":false,"content":"BS3","columnLabels":["UK"],"rowLabels":["Cylinder Connections","Ar"]}]},{"cellsStructured":[{"isLabelCell":true,"content":"Spain"},{"isLabelCell":false,"content":"B50 and packs","columnLabels":["Spain"],"rowLabels":["Available Cyl. Size","?"]},{"isLabelCell":false,"content":"AFNOR Type C","columnLabels":["Spain"],"rowLabels":["Cylinder Connections","N2"]},{"isLabelCell":false,"content":"AFNOR Type C","columnLabels":["Spain"],"rowLabels":["Cylinder Connections","He"]},{"isLabelCell":false,"content":"AFNOR Type C","columnLabels":["Spain"],"rowLabels":["Cylinder Connections","Ar"]}]}]}