{"tableId":"49195920_4202358059267669538-0","start":5260,"end":8892,"primaryAttributesList":[{"primaryAttrCell":[{"content":"Country","rowIndex":0,"columnIndex":0,"dataType":"string","isLabelCell":true,"source":"49195920_4202358059267669538-0"}],"attrValues":[]},{"primaryAttrCell":[{"content":"City","rowIndex":0,"columnIndex":1,"dataType":"string","isLabelCell":true,"source":"49195920_4202358059267669538-0"}],"attrValues":[{"cellAttribute":{"content":"Argentina","rowIndex":1,"columnIndex":1,"dataType":"string","isLabelCell":true,"source":"49195920_4202358059267669538-0"},"cellValue":{"content":"Buenos Aires","rowIndex":1,"columnIndex":1,"dataType":"string","isLabelCell":true,"source":"49195920_4202358059267669538-0"}},{"cellAttribute":{"content":"Ameriflon S.A. Buenos Aires 2160 Olivos - (1636)","rowIndex":2,"columnIndex":1,"dataType":"string","isLabelCell":true,"source":"49195920_4202358059267669538-0"},"cellValue":{"content":"Ameriflon S.A. Buenos Aires 2160 Olivos - (1636)","rowIndex":2,"columnIndex":1,"dataType":"string","isLabelCell":true,"source":"49195920_4202358059267669538-0"}},{"cellAttribute":{"content":"Asia","rowIndex":3,"columnIndex":1,"dataType":"string","isLabelCell":true,"source":"49195920_4202358059267669538-0"},"cellValue":{"content":"Singapore","rowIndex":3,"columnIndex":1,"dataType":"string","isLabelCell":true,"source":"49195920_4202358059267669538-0"}},{"cellAttribute":{"content":"Durabla Asia Pte. Ltd. 50 Bukit Batok St 23 #01-23 Midview Bldg","rowIndex":4,"columnIndex":1,"dataType":"string","isLabelCell":true,"source":"49195920_4202358059267669538-0"},"cellValue":{"content":"Durabla Asia Pte. Ltd. 50 Bukit Batok St 23 #01-23 Midview Bldg","rowIndex":4,"columnIndex":1,"dataType":"string","isLabelCell":true,"source":"49195920_4202358059267669538-0"}},{"cellAttribute":{"content":"Chile","rowIndex":5,"columnIndex":1,"dataType":"string","isLabelCell":true,"source":"49195920_4202358059267669538-0"},"cellValue":{"content":"Recoleta - Santiago","rowIndex":5,"columnIndex":1,"dataType":"string","isLabelCell":true,"source":"49195920_4202358059267669538-0"}},{"cellAttribute":{"content":"Diproplas Ltda El Roble 464","rowIndex":6,"columnIndex":1,"dataType":"string","isLabelCell":true,"source":"49195920_4202358059267669538-0"},"cellValue":{"content":"Diproplas Ltda El Roble 464","rowIndex":6,"columnIndex":1,"dataType":"string","isLabelCell":true,"source":"49195920_4202358059267669538-0"}},{"cellAttribute":{"content":"Chile","rowIndex":7,"columnIndex":1,"dataType":"string","isLabelCell":true,"source":"49195920_4202358059267669538-0"},"cellValue":{"content":"Conchali - Santiago","rowIndex":7,"columnIndex":1,"dataType":"string","isLabelCell":true,"source":"49195920_4202358059267669538-0"}},{"cellAttribute":{"content":"Invenio S.A. Casilla 70087 - Correo 7","rowIndex":8,"columnIndex":1,"dataType":"string","isLabelCell":true,"source":"49195920_4202358059267669538-0"},"cellValue":{"content":"Invenio S.A. Casilla 70087 - Correo 7","rowIndex":8,"columnIndex":1,"dataType":"string","isLabelCell":true,"source":"49195920_4202358059267669538-0"}},{"cellAttribute":{"content":"China","rowIndex":9,"columnIndex":1,"dataType":"string","isLabelCell":true,"source":"49195920_4202358059267669538-0"},"cellValue":{"content":"Hangzhou, Zhejinag","rowIndex":9,"columnIndex":1,"dataType":"string","isLabelCell":true,"source":"49195920_4202358059267669538-0"}},{"cellAttribute":{"content":"Durabla Fluid Controls (Shangyu) Co. Ltd. Hangzhou Hi-Tech Park Bingiang Distrist No. 1193, Bin An Road","rowIndex":10,"columnIndex":1,"dataType":"string","isLabelCell":true,"source":"49195920_4202358059267669538-0"},"cellValue":{"content":"Durabla Fluid Controls (Shangyu) Co. Ltd. Hangzhou Hi-Tech Park Bingiang Distrist No. 1193, Bin An Road","rowIndex":10,"columnIndex":1,"dataType":"string","isLabelCell":true,"source":"49195920_4202358059267669538-0"}},{"cellAttribute":{"content":"India","rowIndex":11,"columnIndex":1,"dataType":"string","isLabelCell":true,"source":"49195920_4202358059267669538-0"},"cellValue":{"content":"Haryana","rowIndex":11,"columnIndex":1,"dataType":"string","isLabelCell":true,"source":"49195920_4202358059267669538-0"}},{"cellAttribute":{"content":"Micro Precision Products Pvt 3, Link Road, Sector - 28 Faridabad - 121008","rowIndex":12,"columnIndex":1,"dataType":"string","isLabelCell":true,"source":"49195920_4202358059267669538-0"},"cellValue":{"content":"Micro Precision Products Pvt 3, Link Road, Sector - 28 Faridabad - 121008","rowIndex":12,"columnIndex":1,"dataType":"string","isLabelCell":true,"source":"49195920_4202358059267669538-0"}},{"cellAttribute":{"content":"Italy","rowIndex":13,"columnIndex":1,"dataType":"string","isLabelCell":true,"source":"49195920_4202358059267669538-0"},"cellValue":{"content":"20125 Milano","rowIndex":13,"columnIndex":1,"dataType":"string","isLabelCell":true,"source":"49195920_4202358059267669538-0"}},{"cellAttribute":{"content":"Eteria S.R.L. P.Iva 03352810968 Viale Monza, 27","rowIndex":14,"columnIndex":1,"dataType":"string","isLabelCell":true,"source":"49195920_4202358059267669538-0"},"cellValue":{"content":"Eteria S.R.L. P.Iva 03352810968 Viale Monza, 27","rowIndex":14,"columnIndex":1,"dataType":"string","isLabelCell":true,"source":"49195920_4202358059267669538-0"}},{"cellAttribute":{"content":"Mexico","rowIndex":15,"columnIndex":1,"dataType":"string","isLabelCell":true,"source":"49195920_4202358059267669538-0"},"cellValue":{"content":"Veracruz e-mail felipe@feseal.com.mx","rowIndex":15,"columnIndex":1,"dataType":"string","isLabelCell":true,"source":"49195920_4202358059267669538-0"}},{"cellAttribute":{"content":"New Zealand","rowIndex":17,"columnIndex":1,"dataType":"string","isLabelCell":true,"source":"49195920_4202358059267669538-0"},"cellValue":{"content":"Avondale, Auckland","rowIndex":17,"columnIndex":1,"dataType":"string","isLabelCell":true,"source":"49195920_4202358059267669538-0"}},{"cellAttribute":{"content":"Grupo Industrial Feseal Y Asociados Sa. De Cv. Col. Centro 96400 Avenida Benito Juarez 1401 Coatzacoalcos,www.feseal.com.mx","rowIndex":16,"columnIndex":1,"dataType":"string","isLabelCell":true,"source":"49195920_4202358059267669538-0"},"cellValue":{"content":"Grupo Industrial Feseal Y Asociados Sa. De Cv. Col. Centro 96400 Avenida Benito Juarez 1401 Coatzacoalcos,www.feseal.com.mx","rowIndex":16,"columnIndex":1,"dataType":"string","isLabelCell":true,"source":"49195920_4202358059267669538-0"}},{"cellAttribute":{"content":"Switzerland","rowIndex":19,"columnIndex":1,"dataType":"string","isLabelCell":true,"source":"49195920_4202358059267669538-0"},"cellValue":{"content":"Zurich","rowIndex":19,"columnIndex":1,"dataType":"string","isLabelCell":true,"source":"49195920_4202358059267669538-0"}},{"cellAttribute":{"content":"Automotive Components Nz Limited 73 Lansford Crescent Po Box 19-025","rowIndex":18,"columnIndex":1,"dataType":"string","isLabelCell":true,"source":"49195920_4202358059267669538-0"},"cellValue":{"content":"Automotive Components Nz Limited 73 Lansford Crescent Po Box 19-025","rowIndex":18,"columnIndex":1,"dataType":"string","isLabelCell":true,"source":"49195920_4202358059267669538-0"}},{"cellAttribute":{"content":"Trinidad \u0026 Tobago","rowIndex":21,"columnIndex":1,"dataType":"string","isLabelCell":true,"source":"49195920_4202358059267669538-0"},"cellValue":{"content":"St. Augustine","rowIndex":21,"columnIndex":1,"dataType":"string","isLabelCell":true,"source":"49195920_4202358059267669538-0"}},{"cellAttribute":{"content":"Aspag Ag Europa-Strasse 14 8152 Glattbrugg","rowIndex":20,"columnIndex":1,"dataType":"string","isLabelCell":true,"source":"49195920_4202358059267669538-0"},"cellValue":{"content":"Aspag Ag Europa-Strasse 14 8152 Glattbrugg","rowIndex":20,"columnIndex":1,"dataType":"string","isLabelCell":true,"source":"49195920_4202358059267669538-0"}},{"cellAttribute":{"content":"United States","rowIndex":23,"columnIndex":1,"dataType":"string","isLabelCell":true,"source":"49195920_4202358059267669538-0"},"cellValue":{"content":"Exton, PA","rowIndex":23,"columnIndex":1,"dataType":"string","isLabelCell":true,"source":"49195920_4202358059267669538-0"}},{"cellAttribute":{"content":"Accurate Industrial Supplies Limited 26 Sellier Street","rowIndex":22,"columnIndex":1,"dataType":"string","isLabelCell":true,"source":"49195920_4202358059267669538-0"},"cellValue":{"content":"Accurate Industrial Supplies Limited 26 Sellier Street","rowIndex":22,"columnIndex":1,"dataType":"string","isLabelCell":true,"source":"49195920_4202358059267669538-0"}},{"cellAttribute":{"content":"Gasket Resources Inc. P.O. Box 565 140 Sheree Blvd","rowIndex":24,"columnIndex":1,"dataType":"string","isLabelCell":true,"source":"49195920_4202358059267669538-0"},"cellValue":{"content":"Gasket Resources Inc. P.O. Box 565 140 Sheree Blvd","rowIndex":24,"columnIndex":1,"dataType":"string","isLabelCell":true,"source":"49195920_4202358059267669538-0"}}]},{"primaryAttrCell":[{"content":"Telephone","rowIndex":0,"columnIndex":2,"dataType":"string","isLabelCell":true,"source":"49195920_4202358059267669538-0"}],"attrValues":[{"cellAttribute":{"content":"Argentina","rowIndex":1,"columnIndex":2,"dataType":"string","isLabelCell":true,"source":"49195920_4202358059267669538-0"},"cellValue":{"content":"(54) 11-4795-7239","rowIndex":1,"columnIndex":2,"dataType":"numeric","isLabelCell":true,"source":"49195920_4202358059267669538-0"}},{"cellAttribute":{"content":"Ameriflon S.A. Buenos Aires 2160 Olivos - (1636)","rowIndex":2,"columnIndex":2,"dataType":"string","isLabelCell":true,"source":"49195920_4202358059267669538-0"},"cellValue":{"content":"Ameriflon S.A. Buenos Aires 2160 Olivos - (1636)","rowIndex":2,"columnIndex":2,"dataType":"string","isLabelCell":true,"source":"49195920_4202358059267669538-0"}},{"cellAttribute":{"content":"Asia","rowIndex":3,"columnIndex":2,"dataType":"string","isLabelCell":true,"source":"49195920_4202358059267669538-0"},"cellValue":{"content":"(656) 316-7067","rowIndex":3,"columnIndex":2,"dataType":"numeric","isLabelCell":true,"source":"49195920_4202358059267669538-0"}},{"cellAttribute":{"content":"Durabla Asia Pte. Ltd. 50 Bukit Batok St 23 #01-23 Midview Bldg","rowIndex":4,"columnIndex":2,"dataType":"string","isLabelCell":true,"source":"49195920_4202358059267669538-0"},"cellValue":{"content":"Durabla Asia Pte. Ltd. 50 Bukit Batok St 23 #01-23 Midview Bldg","rowIndex":4,"columnIndex":2,"dataType":"string","isLabelCell":true,"source":"49195920_4202358059267669538-0"}},{"cellAttribute":{"content":"Chile","rowIndex":5,"columnIndex":2,"dataType":"string","isLabelCell":true,"source":"49195920_4202358059267669538-0"},"cellValue":{"content":"(562) 622-6037","rowIndex":5,"columnIndex":2,"dataType":"numeric","isLabelCell":true,"source":"49195920_4202358059267669538-0"}},{"cellAttribute":{"content":"Diproplas Ltda El Roble 464","rowIndex":6,"columnIndex":2,"dataType":"string","isLabelCell":true,"source":"49195920_4202358059267669538-0"},"cellValue":{"content":"Diproplas Ltda El Roble 464","rowIndex":6,"columnIndex":2,"dataType":"string","isLabelCell":true,"source":"49195920_4202358059267669538-0"}},{"cellAttribute":{"content":"Chile","rowIndex":7,"columnIndex":2,"dataType":"string","isLabelCell":true,"source":"49195920_4202358059267669538-0"},"cellValue":{"content":"56-02-72564100","rowIndex":7,"columnIndex":2,"dataType":"numeric","isLabelCell":true,"source":"49195920_4202358059267669538-0"}},{"cellAttribute":{"content":"Invenio S.A. Casilla 70087 - Correo 7","rowIndex":8,"columnIndex":2,"dataType":"string","isLabelCell":true,"source":"49195920_4202358059267669538-0"},"cellValue":{"content":"Invenio S.A. Casilla 70087 - Correo 7","rowIndex":8,"columnIndex":2,"dataType":"string","isLabelCell":true,"source":"49195920_4202358059267669538-0"}},{"cellAttribute":{"content":"China","rowIndex":9,"columnIndex":2,"dataType":"string","isLabelCell":true,"source":"49195920_4202358059267669538-0"},"cellValue":{"content":"","rowIndex":9,"columnIndex":2,"dataType":"numeric","isLabelCell":true,"source":"49195920_4202358059267669538-0"}},{"cellAttribute":{"content":"Durabla Fluid Controls (Shangyu) Co. Ltd. Hangzhou Hi-Tech Park Bingiang Distrist No. 1193, Bin An Road","rowIndex":10,"columnIndex":2,"dataType":"string","isLabelCell":true,"source":"49195920_4202358059267669538-0"},"cellValue":{"content":"Durabla Fluid Controls (Shangyu) Co. Ltd. Hangzhou Hi-Tech Park Bingiang Distrist No. 1193, Bin An Road","rowIndex":10,"columnIndex":2,"dataType":"string","isLabelCell":true,"source":"49195920_4202358059267669538-0"}},{"cellAttribute":{"content":"India","rowIndex":11,"columnIndex":2,"dataType":"string","isLabelCell":true,"source":"49195920_4202358059267669538-0"},"cellValue":{"content":"","rowIndex":11,"columnIndex":2,"dataType":"numeric","isLabelCell":true,"source":"49195920_4202358059267669538-0"}},{"cellAttribute":{"content":"Micro Precision Products Pvt 3, Link Road, Sector - 28 Faridabad - 121008","rowIndex":12,"columnIndex":2,"dataType":"string","isLabelCell":true,"source":"49195920_4202358059267669538-0"},"cellValue":{"content":"Micro Precision Products Pvt 3, Link Road, Sector - 28 Faridabad - 121008","rowIndex":12,"columnIndex":2,"dataType":"string","isLabelCell":true,"source":"49195920_4202358059267669538-0"}},{"cellAttribute":{"content":"Italy","rowIndex":13,"columnIndex":2,"dataType":"string","isLabelCell":true,"source":"49195920_4202358059267669538-0"},"cellValue":{"content":"02 923 70196","rowIndex":13,"columnIndex":2,"dataType":"numeric","isLabelCell":true,"source":"49195920_4202358059267669538-0"}},{"cellAttribute":{"content":"Eteria S.R.L. P.Iva 03352810968 Viale Monza, 27","rowIndex":14,"columnIndex":2,"dataType":"string","isLabelCell":true,"source":"49195920_4202358059267669538-0"},"cellValue":{"content":"Eteria S.R.L. P.Iva 03352810968 Viale Monza, 27","rowIndex":14,"columnIndex":2,"dataType":"string","isLabelCell":true,"source":"49195920_4202358059267669538-0"}},{"cellAttribute":{"content":"Mexico","rowIndex":15,"columnIndex":2,"dataType":"string","isLabelCell":true,"source":"49195920_4202358059267669538-0"},"cellValue":{"content":"921 2147517","rowIndex":15,"columnIndex":2,"dataType":"numeric","isLabelCell":true,"source":"49195920_4202358059267669538-0"}},{"cellAttribute":{"content":"New Zealand","rowIndex":17,"columnIndex":2,"dataType":"string","isLabelCell":true,"source":"49195920_4202358059267669538-0"},"cellValue":{"content":"64 9 828 4119","rowIndex":17,"columnIndex":2,"dataType":"numeric","isLabelCell":true,"source":"49195920_4202358059267669538-0"}},{"cellAttribute":{"content":"Grupo Industrial Feseal Y Asociados Sa. De Cv. Col. Centro 96400 Avenida Benito Juarez 1401 Coatzacoalcos,www.feseal.com.mx","rowIndex":16,"columnIndex":2,"dataType":"string","isLabelCell":true,"source":"49195920_4202358059267669538-0"},"cellValue":{"content":"Grupo Industrial Feseal Y Asociados Sa. De Cv. Col. Centro 96400 Avenida Benito Juarez 1401 Coatzacoalcos,www.feseal.com.mx","rowIndex":16,"columnIndex":2,"dataType":"string","isLabelCell":true,"source":"49195920_4202358059267669538-0"}},{"cellAttribute":{"content":"Switzerland","rowIndex":19,"columnIndex":2,"dataType":"string","isLabelCell":true,"source":"49195920_4202358059267669538-0"},"cellValue":{"content":"044/828 1530","rowIndex":19,"columnIndex":2,"dataType":"numeric","isLabelCell":true,"source":"49195920_4202358059267669538-0"}},{"cellAttribute":{"content":"Automotive Components Nz Limited 73 Lansford Crescent Po Box 19-025","rowIndex":18,"columnIndex":2,"dataType":"string","isLabelCell":true,"source":"49195920_4202358059267669538-0"},"cellValue":{"content":"Automotive Components Nz Limited 73 Lansford Crescent Po Box 19-025","rowIndex":18,"columnIndex":2,"dataType":"string","isLabelCell":true,"source":"49195920_4202358059267669538-0"}},{"cellAttribute":{"content":"Trinidad \u0026 Tobago","rowIndex":21,"columnIndex":2,"dataType":"string","isLabelCell":true,"source":"49195920_4202358059267669538-0"},"cellValue":{"content":"(868) 662-5193","rowIndex":21,"columnIndex":2,"dataType":"numeric","isLabelCell":true,"source":"49195920_4202358059267669538-0"}},{"cellAttribute":{"content":"Aspag Ag Europa-Strasse 14 8152 Glattbrugg","rowIndex":20,"columnIndex":2,"dataType":"string","isLabelCell":true,"source":"49195920_4202358059267669538-0"},"cellValue":{"content":"Aspag Ag Europa-Strasse 14 8152 Glattbrugg","rowIndex":20,"columnIndex":2,"dataType":"string","isLabelCell":true,"source":"49195920_4202358059267669538-0"}},{"cellAttribute":{"content":"United States","rowIndex":23,"columnIndex":2,"dataType":"string","isLabelCell":true,"source":"49195920_4202358059267669538-0"},"cellValue":{"content":"(610) 363-5800","rowIndex":23,"columnIndex":2,"dataType":"numeric","isLabelCell":true,"source":"49195920_4202358059267669538-0"}},{"cellAttribute":{"content":"Accurate Industrial Supplies Limited 26 Sellier Street","rowIndex":22,"columnIndex":2,"dataType":"string","isLabelCell":true,"source":"49195920_4202358059267669538-0"},"cellValue":{"content":"Accurate Industrial Supplies Limited 26 Sellier Street","rowIndex":22,"columnIndex":2,"dataType":"string","isLabelCell":true,"source":"49195920_4202358059267669538-0"}},{"cellAttribute":{"content":"Gasket Resources Inc. P.O. Box 565 140 Sheree Blvd","rowIndex":24,"columnIndex":2,"dataType":"string","isLabelCell":true,"source":"49195920_4202358059267669538-0"},"cellValue":{"content":"Gasket Resources Inc. P.O. Box 565 140 Sheree Blvd","rowIndex":24,"columnIndex":2,"dataType":"string","isLabelCell":true,"source":"49195920_4202358059267669538-0"}}]},{"primaryAttrCell":[{"content":"Fax.","rowIndex":0,"columnIndex":3,"dataType":"string","isLabelCell":true,"source":"49195920_4202358059267669538-0"}],"attrValues":[{"cellAttribute":{"content":"Argentina","rowIndex":1,"columnIndex":3,"dataType":"string","isLabelCell":true,"source":"49195920_4202358059267669538-0"},"cellValue":{"content":"(54) 11-4795-7239","rowIndex":1,"columnIndex":3,"dataType":"numeric","isLabelCell":true,"source":"49195920_4202358059267669538-0"}},{"cellAttribute":{"content":"Ameriflon S.A. Buenos Aires 2160 Olivos - (1636)","rowIndex":2,"columnIndex":3,"dataType":"string","isLabelCell":true,"source":"49195920_4202358059267669538-0"},"cellValue":{"content":"Ameriflon S.A. Buenos Aires 2160 Olivos - (1636)","rowIndex":2,"columnIndex":3,"dataType":"string","isLabelCell":true,"source":"49195920_4202358059267669538-0"}},{"cellAttribute":{"content":"Asia","rowIndex":3,"columnIndex":3,"dataType":"string","isLabelCell":true,"source":"49195920_4202358059267669538-0"},"cellValue":{"content":"(656) 316-7068","rowIndex":3,"columnIndex":3,"dataType":"numeric","isLabelCell":true,"source":"49195920_4202358059267669538-0"}},{"cellAttribute":{"content":"Durabla Asia Pte. Ltd. 50 Bukit Batok St 23 #01-23 Midview Bldg","rowIndex":4,"columnIndex":3,"dataType":"string","isLabelCell":true,"source":"49195920_4202358059267669538-0"},"cellValue":{"content":"Durabla Asia Pte. Ltd. 50 Bukit Batok St 23 #01-23 Midview Bldg","rowIndex":4,"columnIndex":3,"dataType":"string","isLabelCell":true,"source":"49195920_4202358059267669538-0"}},{"cellAttribute":{"content":"Chile","rowIndex":5,"columnIndex":3,"dataType":"string","isLabelCell":true,"source":"49195920_4202358059267669538-0"},"cellValue":{"content":"(562) 621-4972","rowIndex":5,"columnIndex":3,"dataType":"numeric","isLabelCell":true,"source":"49195920_4202358059267669538-0"}},{"cellAttribute":{"content":"Diproplas Ltda El Roble 464","rowIndex":6,"columnIndex":3,"dataType":"string","isLabelCell":true,"source":"49195920_4202358059267669538-0"},"cellValue":{"content":"Diproplas Ltda El Roble 464","rowIndex":6,"columnIndex":3,"dataType":"string","isLabelCell":true,"source":"49195920_4202358059267669538-0"}},{"cellAttribute":{"content":"Chile","rowIndex":7,"columnIndex":3,"dataType":"string","isLabelCell":true,"source":"49195920_4202358059267669538-0"},"cellValue":{"content":"56-02-7564160","rowIndex":7,"columnIndex":3,"dataType":"numeric","isLabelCell":true,"source":"49195920_4202358059267669538-0"}},{"cellAttribute":{"content":"Invenio S.A. Casilla 70087 - Correo 7","rowIndex":8,"columnIndex":3,"dataType":"string","isLabelCell":true,"source":"49195920_4202358059267669538-0"},"cellValue":{"content":"Invenio S.A. Casilla 70087 - Correo 7","rowIndex":8,"columnIndex":3,"dataType":"string","isLabelCell":true,"source":"49195920_4202358059267669538-0"}},{"cellAttribute":{"content":"China","rowIndex":9,"columnIndex":3,"dataType":"string","isLabelCell":true,"source":"49195920_4202358059267669538-0"},"cellValue":{"content":"","rowIndex":9,"columnIndex":3,"dataType":"numeric","isLabelCell":true,"source":"49195920_4202358059267669538-0"}},{"cellAttribute":{"content":"Durabla Fluid Controls (Shangyu) Co. Ltd. Hangzhou Hi-Tech Park Bingiang Distrist No. 1193, Bin An Road","rowIndex":10,"columnIndex":3,"dataType":"string","isLabelCell":true,"source":"49195920_4202358059267669538-0"},"cellValue":{"content":"Durabla Fluid Controls (Shangyu) Co. Ltd. Hangzhou Hi-Tech Park Bingiang Distrist No. 1193, Bin An Road","rowIndex":10,"columnIndex":3,"dataType":"string","isLabelCell":true,"source":"49195920_4202358059267669538-0"}},{"cellAttribute":{"content":"India","rowIndex":11,"columnIndex":3,"dataType":"string","isLabelCell":true,"source":"49195920_4202358059267669538-0"},"cellValue":{"content":"","rowIndex":11,"columnIndex":3,"dataType":"numeric","isLabelCell":true,"source":"49195920_4202358059267669538-0"}},{"cellAttribute":{"content":"Micro Precision Products Pvt 3, Link Road, Sector - 28 Faridabad - 121008","rowIndex":12,"columnIndex":3,"dataType":"string","isLabelCell":true,"source":"49195920_4202358059267669538-0"},"cellValue":{"content":"Micro Precision Products Pvt 3, Link Road, Sector - 28 Faridabad - 121008","rowIndex":12,"columnIndex":3,"dataType":"string","isLabelCell":true,"source":"49195920_4202358059267669538-0"}},{"cellAttribute":{"content":"Italy","rowIndex":13,"columnIndex":3,"dataType":"string","isLabelCell":true,"source":"49195920_4202358059267669538-0"},"cellValue":{"content":"02 921 02475","rowIndex":13,"columnIndex":3,"dataType":"numeric","isLabelCell":true,"source":"49195920_4202358059267669538-0"}},{"cellAttribute":{"content":"Eteria S.R.L. P.Iva 03352810968 Viale Monza, 27","rowIndex":14,"columnIndex":3,"dataType":"string","isLabelCell":true,"source":"49195920_4202358059267669538-0"},"cellValue":{"content":"Eteria S.R.L. P.Iva 03352810968 Viale Monza, 27","rowIndex":14,"columnIndex":3,"dataType":"string","isLabelCell":true,"source":"49195920_4202358059267669538-0"}},{"cellAttribute":{"content":"Mexico","rowIndex":15,"columnIndex":3,"dataType":"string","isLabelCell":true,"source":"49195920_4202358059267669538-0"},"cellValue":{"content":"921 2147519","rowIndex":15,"columnIndex":3,"dataType":"numeric","isLabelCell":true,"source":"49195920_4202358059267669538-0"}},{"cellAttribute":{"content":"New Zealand","rowIndex":17,"columnIndex":3,"dataType":"string","isLabelCell":true,"source":"49195920_4202358059267669538-0"},"cellValue":{"content":"64 9 828 9719","rowIndex":17,"columnIndex":3,"dataType":"numeric","isLabelCell":true,"source":"49195920_4202358059267669538-0"}},{"cellAttribute":{"content":"Grupo Industrial Feseal Y Asociados Sa. De Cv. Col. Centro 96400 Avenida Benito Juarez 1401 Coatzacoalcos,www.feseal.com.mx","rowIndex":16,"columnIndex":3,"dataType":"string","isLabelCell":true,"source":"49195920_4202358059267669538-0"},"cellValue":{"content":"Grupo Industrial Feseal Y Asociados Sa. De Cv. Col. Centro 96400 Avenida Benito Juarez 1401 Coatzacoalcos,www.feseal.com.mx","rowIndex":16,"columnIndex":3,"dataType":"string","isLabelCell":true,"source":"49195920_4202358059267669538-0"}},{"cellAttribute":{"content":"Switzerland","rowIndex":19,"columnIndex":3,"dataType":"string","isLabelCell":true,"source":"49195920_4202358059267669538-0"},"cellValue":{"content":"044/828 1535","rowIndex":19,"columnIndex":3,"dataType":"numeric","isLabelCell":true,"source":"49195920_4202358059267669538-0"}},{"cellAttribute":{"content":"Automotive Components Nz Limited 73 Lansford Crescent Po Box 19-025","rowIndex":18,"columnIndex":3,"dataType":"string","isLabelCell":true,"source":"49195920_4202358059267669538-0"},"cellValue":{"content":"Automotive Components Nz Limited 73 Lansford Crescent Po Box 19-025","rowIndex":18,"columnIndex":3,"dataType":"string","isLabelCell":true,"source":"49195920_4202358059267669538-0"}},{"cellAttribute":{"content":"Trinidad \u0026 Tobago","rowIndex":21,"columnIndex":3,"dataType":"string","isLabelCell":true,"source":"49195920_4202358059267669538-0"},"cellValue":{"content":"(868) 645-3977","rowIndex":21,"columnIndex":3,"dataType":"numeric","isLabelCell":true,"source":"49195920_4202358059267669538-0"}},{"cellAttribute":{"content":"Aspag Ag Europa-Strasse 14 8152 Glattbrugg","rowIndex":20,"columnIndex":3,"dataType":"string","isLabelCell":true,"source":"49195920_4202358059267669538-0"},"cellValue":{"content":"Aspag Ag Europa-Strasse 14 8152 Glattbrugg","rowIndex":20,"columnIndex":3,"dataType":"string","isLabelCell":true,"source":"49195920_4202358059267669538-0"}},{"cellAttribute":{"content":"United States","rowIndex":23,"columnIndex":3,"dataType":"string","isLabelCell":true,"source":"49195920_4202358059267669538-0"},"cellValue":{"content":"(610) 363-5881","rowIndex":23,"columnIndex":3,"dataType":"numeric","isLabelCell":true,"source":"49195920_4202358059267669538-0"}},{"cellAttribute":{"content":"Accurate Industrial Supplies Limited 26 Sellier Street","rowIndex":22,"columnIndex":3,"dataType":"string","isLabelCell":true,"source":"49195920_4202358059267669538-0"},"cellValue":{"content":"Accurate Industrial Supplies Limited 26 Sellier Street","rowIndex":22,"columnIndex":3,"dataType":"string","isLabelCell":true,"source":"49195920_4202358059267669538-0"}},{"cellAttribute":{"content":"Gasket Resources Inc. P.O. Box 565 140 Sheree Blvd","rowIndex":24,"columnIndex":3,"dataType":"string","isLabelCell":true,"source":"49195920_4202358059267669538-0"},"cellValue":{"content":"Gasket Resources Inc. P.O. Box 565 140 Sheree Blvd","rowIndex":24,"columnIndex":3,"dataType":"string","isLabelCell":true,"source":"49195920_4202358059267669538-0"}}]}]}