{"tableId":"55050415_9125020272144403397-0","start":16036,"end":17585,"primaryAttributesList":[{"primaryAttrCell":[{"content":"Cost","rowIndex":0,"columnIndex":0,"dataType":"string","isLabelCell":true,"source":"55050415_9125020272144403397-0"}],"attrValues":[{"cellAttribute":{"content":"Victoria, Australia","rowIndex":1,"columnIndex":0,"dataType":"string","isLabelCell":true,"source":"55050415_9125020272144403397-0"},"cellValue":{"content":"AUD $660","rowIndex":1,"columnIndex":0,"dataType":"string","isLabelCell":true,"source":"55050415_9125020272144403397-0"}},{"cellAttribute":{"content":"Germany","rowIndex":2,"columnIndex":0,"dataType":"string","isLabelCell":true,"source":"55050415_9125020272144403397-0"},"cellValue":{"content":"EUR ?327","rowIndex":2,"columnIndex":0,"dataType":"string","isLabelCell":true,"source":"55050415_9125020272144403397-0"}},{"cellAttribute":{"content":"Germany","rowIndex":3,"columnIndex":0,"dataType":"string","isLabelCell":true,"source":"55050415_9125020272144403397-0"},"cellValue":{"content":"EUR ?387","rowIndex":3,"columnIndex":0,"dataType":"string","isLabelCell":true,"source":"55050415_9125020272144403397-0"}},{"cellAttribute":{"content":"United Kingdom","rowIndex":4,"columnIndex":0,"dataType":"string","isLabelCell":true,"source":"55050415_9125020272144403397-0"},"cellValue":{"content":"GBP ?246","rowIndex":4,"columnIndex":0,"dataType":"string","isLabelCell":true,"source":"55050415_9125020272144403397-0"}},{"cellAttribute":{"content":"Germany","rowIndex":5,"columnIndex":0,"dataType":"string","isLabelCell":true,"source":"55050415_9125020272144403397-0"},"cellValue":{"content":"EUR ?321","rowIndex":5,"columnIndex":0,"dataType":"string","isLabelCell":true,"source":"55050415_9125020272144403397-0"}},{"cellAttribute":{"content":"New South Wales, Australia","rowIndex":6,"columnIndex":0,"dataType":"string","isLabelCell":true,"source":"55050415_9125020272144403397-0"},"cellValue":{"content":"AUD $1,025","rowIndex":6,"columnIndex":0,"dataType":"string","isLabelCell":true,"source":"55050415_9125020272144403397-0"}},{"cellAttribute":{"content":"United States","rowIndex":7,"columnIndex":0,"dataType":"string","isLabelCell":true,"source":"55050415_9125020272144403397-0"},"cellValue":{"content":"USD $510","rowIndex":7,"columnIndex":0,"dataType":"string","isLabelCell":true,"source":"55050415_9125020272144403397-0"}},{"cellAttribute":{"content":"United States","rowIndex":8,"columnIndex":0,"dataType":"string","isLabelCell":true,"source":"55050415_9125020272144403397-0"},"cellValue":{"content":"USD $510","rowIndex":8,"columnIndex":0,"dataType":"string","isLabelCell":true,"source":"55050415_9125020272144403397-0"}},{"cellAttribute":{"content":"United States","rowIndex":9,"columnIndex":0,"dataType":"string","isLabelCell":true,"source":"55050415_9125020272144403397-0"},"cellValue":{"content":"USD $375","rowIndex":9,"columnIndex":0,"dataType":"string","isLabelCell":true,"source":"55050415_9125020272144403397-0"}},{"cellAttribute":{"content":"New Jersey, United States","rowIndex":10,"columnIndex":0,"dataType":"string","isLabelCell":true,"source":"55050415_9125020272144403397-0"},"cellValue":{"content":"USD $452","rowIndex":10,"columnIndex":0,"dataType":"string","isLabelCell":true,"source":"55050415_9125020272144403397-0"}}]},{"primaryAttrCell":[{"content":"Location","rowIndex":0,"columnIndex":1,"dataType":"string","isLabelCell":true,"source":"55050415_9125020272144403397-0"}],"attrValues":[]},{"primaryAttrCell":[{"content":"Date","rowIndex":0,"columnIndex":2,"dataType":"string","isLabelCell":true,"source":"55050415_9125020272144403397-0"}],"attrValues":[{"cellAttribute":{"content":"Victoria, Australia","rowIndex":1,"columnIndex":2,"dataType":"string","isLabelCell":true,"source":"55050415_9125020272144403397-0"},"cellValue":{"content":"14 March, 2011","rowIndex":1,"columnIndex":2,"dataType":"string","isLabelCell":true,"source":"55050415_9125020272144403397-0"}},{"cellAttribute":{"content":"Germany","rowIndex":2,"columnIndex":2,"dataType":"string","isLabelCell":true,"source":"55050415_9125020272144403397-0"},"cellValue":{"content":"16 January, 2011","rowIndex":2,"columnIndex":2,"dataType":"string","isLabelCell":true,"source":"55050415_9125020272144403397-0"}},{"cellAttribute":{"content":"Germany","rowIndex":3,"columnIndex":2,"dataType":"string","isLabelCell":true,"source":"55050415_9125020272144403397-0"},"cellValue":{"content":"03 October, 2010","rowIndex":3,"columnIndex":2,"dataType":"string","isLabelCell":true,"source":"55050415_9125020272144403397-0"}},{"cellAttribute":{"content":"United Kingdom","rowIndex":4,"columnIndex":2,"dataType":"string","isLabelCell":true,"source":"55050415_9125020272144403397-0"},"cellValue":{"content":"03 October, 2010","rowIndex":4,"columnIndex":2,"dataType":"string","isLabelCell":true,"source":"55050415_9125020272144403397-0"}},{"cellAttribute":{"content":"Germany","rowIndex":5,"columnIndex":2,"dataType":"string","isLabelCell":true,"source":"55050415_9125020272144403397-0"},"cellValue":{"content":"19 September, 2010","rowIndex":5,"columnIndex":2,"dataType":"string","isLabelCell":true,"source":"55050415_9125020272144403397-0"}},{"cellAttribute":{"content":"New South Wales, Australia","rowIndex":6,"columnIndex":2,"dataType":"string","isLabelCell":true,"source":"55050415_9125020272144403397-0"},"cellValue":{"content":"02 October, 2009","rowIndex":6,"columnIndex":2,"dataType":"string","isLabelCell":true,"source":"55050415_9125020272144403397-0"}},{"cellAttribute":{"content":"United States","rowIndex":7,"columnIndex":2,"dataType":"string","isLabelCell":true,"source":"55050415_9125020272144403397-0"},"cellValue":{"content":"13 December, 2007","rowIndex":7,"columnIndex":2,"dataType":"string","isLabelCell":true,"source":"55050415_9125020272144403397-0"}},{"cellAttribute":{"content":"United States","rowIndex":8,"columnIndex":2,"dataType":"string","isLabelCell":true,"source":"55050415_9125020272144403397-0"},"cellValue":{"content":"13 December, 2007","rowIndex":8,"columnIndex":2,"dataType":"string","isLabelCell":true,"source":"55050415_9125020272144403397-0"}},{"cellAttribute":{"content":"United States","rowIndex":9,"columnIndex":2,"dataType":"string","isLabelCell":true,"source":"55050415_9125020272144403397-0"},"cellValue":{"content":"20 November, 2007","rowIndex":9,"columnIndex":2,"dataType":"string","isLabelCell":true,"source":"55050415_9125020272144403397-0"}},{"cellAttribute":{"content":"New Jersey, United States","rowIndex":10,"columnIndex":2,"dataType":"string","isLabelCell":true,"source":"55050415_9125020272144403397-0"},"cellValue":{"content":"07 October, 2007","rowIndex":10,"columnIndex":2,"dataType":"string","isLabelCell":true,"source":"55050415_9125020272144403397-0"}}]}]}